{"runInfo": {"sut": "OJP", "workload": "W3_SLOW_QUERY", "loadMode": "open-loop", "targetRps": 200, "concurrency": 0, "poolSize": 48, "instanceId": 4, "totalInstances": 8, "configuredDbConnectionBudget": 48, "configuredReplicas": 8, "seed": 42, "durationSeconds": 1800, "timestamp": "2026-05-12T00:27:57Z", "openLoopAttemptedOps": 476204, "openLoopMissedOpportunities": 2987, "openLoopSchedulingDelayMs": 19021.213922, "clientPooling": "none", "ojpVirtualConnectionMode": "PER_WORKER", "ojpPoolSharing": "SHARED", "ojpPropertiesUsed": {"ojp.slowQueryThresholdMs": "1000", "ojp.connection.pool.minimumIdle": "48", "ojp.queueLimit": "200", "ojp.connection.pool.maxLifetime": "1800000", "ojp.connection.pool.connectionTimeout": "30000", "ojp.connection.pool.idleTimeout": "600000"}, "clientVirtualConnectionsOpenedTotal": 352432, "clientVirtualConnectionsMaxConcurrent": 40}, "attemptedRps": 110.24903268134014, "achievedThroughputRps": 109.6585631909066, "errorRate": 0.005498385252570871, "totalRequests": 278991, "failedRequests": 1534, "latencyMs": {"p50": 5.791, "p95": 25.951, "p99": 209.663, "p999": 30048.255, "max": 60129.279, "mean": 145.96891595814844}, "errorsByType": {"other": 40, "sql_exception": 1494}, "firstErrorMessageByType": {"sql_exception": "Unexpected error: Timeout waiting for admission control slot for operation: e7282124a6fbdd3c"}, "appCpuMedian": 0.421941045644908, "gcPauseMsTotal": 3524}